ge_sm/__init__.py
ge_sm/control.py
ge_sm/control_details.py
ge_sm/common/__init__.py
ge_sm/common/create_database_tables.py
ge_sm/common/database_connection.py
ge_sm/common/helper_funcs.py
ge_sm/common/logger.py
ge_sm/common/secrets.py
ge_sm/facebook_code/__init__.py
ge_sm/facebook_code/api_code/__init__.py
ge_sm/facebook_code/api_code/facebook_API.py
ge_sm/facebook_code/api_code/facebook_secrets.py
ge_sm/facebook_code/data_creation/__init__.py
ge_sm/facebook_code/data_creation/query_ads.py
ge_sm/facebook_code/data_creation/query_pages.py
ge_sm/facebook_code/data_creation/query_posts.py
ge_sm/facebook_code/settings/__init__.py
ge_sm/facebook_code/settings/chaa_jaa_ad_account_settings.py
ge_sm/facebook_code/settings/chaa_jaa_settings.py
ge_sm/google_analytics_code/__init__.py
ge_sm/google_analytics_code/api_code/__init__.py
ge_sm/google_analytics_code/api_code/google_analytics_api.py
ge_sm/google_analytics_code/data_creation/__init__.py
ge_sm/google_analytics_code/data_creation/query_reports.py
ge_sm/google_analytics_code/settings/__init__.py
ge_sm/google_analytics_code/settings/chaa_jaa_settings.py
ge_sm/youtube_code/__init__.py
ge_sm/youtube_code/api_code/__init__.py
ge_sm/youtube_code/api_code/youtube_analytics_api.py
ge_sm/youtube_code/data_creation/__init__.py
ge_sm/youtube_code/data_creation/query_reports.py
ge_sm/youtube_code/settings/__init__.py
ge_sm/youtube_code/settings/chaa_jaa_settings.py
ge_sm-0.0.18.dist-info/DESCRIPTION.rst
ge_sm-0.0.18.dist-info/METADATA
ge_sm-0.0.18.dist-info/RECORD
ge_sm-0.0.18.dist-info/WHEEL
ge_sm-0.0.18.dist-info/metadata.json
ge_sm-0.0.18.dist-info/top_level.txt
