Metadata-Version: 2.0
Name: ge-sm
Version: 0.0.18
Summary: A python applications.
Home-page: UNKNOWN
Author: Praekelt.org
Author-email: dev@praekelt.org
License: BSD
Keywords: ge_sm
Platform: UNKNOWN
Classifier: Intended Audience :: Developers
Classifier: Natural Language :: English
Classifier: Programming Language :: Python :: 3.6
Requires-Dist: SQLAlchemy (==1.3.8)
Requires-Dist: facebook-business (==6.0.4)
Requires-Dist: facebook-sdk (==3.1.0)
Requires-Dist: google-api-python-client (==1.7.11)
Requires-Dist: httplib2 (==0.13.1)
Requires-Dist: oauth2client (==4.1.3)
Requires-Dist: pandas (==0.25.1)
Requires-Dist: psycopg2
Requires-Dist: sqlalchemy-redshift (==0.7.5)
